qartez/__init__.py
qartez/conf.py
qartez/constants.py
qartez/defaults.py
qartez/models.py
qartez/settings.py
qartez/sitemaps.py
qartez/views.py
qartez/templates/qartez/images_sitemap.xml
qartez/templates/qartez/rel_alternate_hreflang_sitemap.xml
qartez/tests/__init__.py
qartez/tests/base.py
qartez/tests/test_sitemaps.py
django_qartez-0.8.1.dist-info/LICENSE_GPL2.0.txt
django_qartez-0.8.1.dist-info/LICENSE_LGPL_2.1.txt
django_qartez-0.8.1.dist-info/METADATA
django_qartez-0.8.1.dist-info/WHEEL
django_qartez-0.8.1.dist-info/top_level.txt
django_qartez-0.8.1.dist-info/RECORD
