Metadata-Version: 1.2
Name: django-qartez
Version: 0.8.1
Summary: Additional XML sitemap functionality for Django
Home-page: https://github.com/barseghyanartur/django-qartez/
Author: Artur Barseghyan
Author-email: artur.barseghyan@gmail.com
License: GPL 2.0/LGPL 2.1
Project-URL: Bug Tracker, https://github.com/barseghyanartur/django-qartez/issues
Project-URL: Documentation, https://django-qartez.readthedocs.io/
Project-URL: Source Code, https://github.com/barseghyanartur/django-qartez/
Project-URL: Changelog, https://django-qartez.readthedocs.io/en/latest/changelog.html
Keywords: xml sitemaps,images sitemaps,django,app,python
Platform: UNKNOWN
Classifier: Programming Language :: Python
Classifier: Programming Language :: Python :: 2.7
Classifier: Programming Language :: Python :: 3
Classifier: Programming Language :: Python :: 3.5
Classifier: Programming Language :: Python :: 3.6
Classifier: Programming Language :: Python :: 3.7
Classifier: Programming Language :: Python :: 3.8
Classifier: Environment :: Web Environment
Classifier: Framework :: Django
Classifier: Intended Audience :: Developers
Classifier: Operating System :: OS Independent
Classifier: Development Status :: 5 - Production/Stable
Classifier: License :: OSI Approved :: GNU General Public License v2 (GPLv2)
Classifier: License :: OSI Approved :: GNU Lesser General Public License v2 or later (LGPLv2+)
